mlflow_iap_token/.pytest_cache/.gitignore
mlflow_iap_token/.pytest_cache/CACHEDIR.TAG
mlflow_iap_token/.pytest_cache/README.md
mlflow_iap_token/.pytest_cache/v/cache/nodeids
mlflow_iap_token/.pytest_cache/v/cache/stepwise
mlflow_iap_token/__init__.py
mlflow_iap_token/iap_token.py
mlflow_iap_token/test.py
mlflow_iap_token-0.3.0.dist-info/entry_points.txt
mlflow_iap_token-0.3.0.dist-info/WHEEL
mlflow_iap_token-0.3.0.dist-info/METADATA
mlflow_iap_token-0.3.0.dist-info/RECORD
