Metadata-Version: 2.1
Name: mlflow-iap-token
Version: 0.3.0
Summary: 
Author: Myung Kim
Author-email: agilemlops@gmail.com
Requires-Python: >=3.7,<4.0
Classifier: Programming Language :: Python :: 3
Classifier: Programming Language :: Python :: 3.7
Classifier: Programming Language :: Python :: 3.8
Classifier: Programming Language :: Python :: 3.9
Requires-Dist: google-auth (>=2.3.3,<3.0.0)
Requires-Dist: mlflow-skinny (>=1.21.0,<2.0.0)
